{
  "code": "A00000",
  "data": {
    "1305432785010006": {
      "voteId": "1305432785010006",
      "mainTitle": "主站-选手投票第三轮复制",
      "order": 1,
      "childs": [
        {
          "vcId": "0206136078020874",
          "title": "青春有你3 第三轮选手投票",
          "totalNum": 0,
          "optionType": 1,
          "options": [
            {
              "oid": "0232609364030731",
              "text": "常华森",
              "optionId": "10",
              "pageUrl": "",
              "picUrl": "https://u6.iqiyipic.com/feige/20210129/18/5b/feige_5b18f696993148c89c51487397d62552_default.jpg",
              "userCouldJoinTimes": 2,
              "userJoinTimes": 0,
              "todayHasJoined": false,
              "runTimes": 0,
              "showNum": 0,
              "kv": "{\"biaoshi\":\"changhuasen\",\"people_state\":\"1\",\"uid\":\"1395811896456466\"}",
              "canVote": 0
            },
            {
              "oid": "0735525988030245",
              "text": "陈俊豪",
              "optionId": "11",
              "pageUrl": "",
              "picUrl": "https://u7.iqiyipic.com/feige/20210129/9b/21/feige_219b8936c7a343c68225eb76d6069126_default.jpg",
              "userCouldJoinTimes": 2,
              "userJoinTimes": 0,
              "todayHasJoined": false,
              "runTimes": 0,
              "showNum": 0,
              "kv": "{\"biaoshi\":\"chenjunhao\",\"people_state\":\"1\",\"uid\":\"1416229868807080\"}",
              "canVote": 0
            },
            {
              "oid": "1272108067030902",
              "text": "草鱼",
              "optionId": "16",
              "pageUrl": "",
              "picUrl": "https://u9.iqiyipic.com/feige/20210129/ff/b0/feige_b0ff02405cb2427cbf0a58b7edd4f241_default.jpg",
              "userCouldJoinTimes": 2,
              "userJoinTimes": 0,
              "todayHasJoined": false,
              "runTimes": 0,
              "showNum": 0,
              "kv": "{\"biaoshi\":\"caoyu\",\"people_state\":\"1\",\"uid\":\"1563604410\"}",
              "canVote": 0
            },
            {
              "oid": "0631426853030955",
              "text": "陈誉庚",
              "optionId": "18",
              "pageUrl": "",
              "picUrl": "https://u2.iqiyipic.com/feige/20210129/bc/3a/feige_3abc0b40c3284a4dbe87d076e3845fab_default.jpg",
              "userCouldJoinTimes": 2,
              "userJoinTimes": 0,
              "todayHasJoined": false,
              "runTimes": 0,
              "showNum": 0,
              "kv": "{\"biaoshi\":\"chenyugeng\",\"people_state\":\"1\",\"uid\":\"1419508774499624\"}",
              "canVote": 0
            },
            {
              "oid": "1234727097030968",
              "text": "杜天宇",
              "optionId": "22",
              "pageUrl": "",
              "picUrl": "https://u2.iqiyipic.com/feige/20210129/1c/a8/feige_a81c0e9374ef4018843c8de0309ddf46_default.jpg",
              "userCouldJoinTimes": 2,
              "userJoinTimes": 0,
              "todayHasJoined": false,
              "runTimes": 0,
              "showNum": 0,
              "kv": "{\"biaoshi\":\"dutianyu\",\"people_state\":\"1\",\"uid\":\"1419432337342915\"}",
              "canVote": 0
            },
            {
              "oid": "1264208280030383",
              "text": "邓孝慈",
              "optionId": "23",
              "pageUrl": "",
              "picUrl": "https://u6.iqiyipic.com/feige/20210129/be/f7/feige_f7bef81aa4384340b6ac5a00bb4de3b0_default.jpg",
              "userCouldJoinTimes": 2,
              "userJoinTimes": 0,
              "todayHasJoined": false,
              "runTimes": 0,
              "showNum": 0,
              "kv": "{\"biaoshi\":\"dengxiaoci\",\"people_state\":\"1\",\"uid\":\"1419445926887887\"}",
              "canVote": 0
            },
            {
              "oid": "1217342843030043",
              "text": "段星星",
              "optionId": "24",
              "pageUrl": "",
              "picUrl": "https://u9.iqiyipic.com/feige/20210129/3d/74/feige_743d8a4dae9d4520949de649b11ada0d_default.jpg",
              "userCouldJoinTimes": 2,
              "userJoinTimes": 0,
              "todayHasJoined": false,
              "runTimes": 0,
              "showNum": 0,
              "kv": "{\"biaoshi\":\"duanxingxing\",\"people_state\":\"1\",\"uid\":\"1413195373749145\"}",
              "canVote": 0
            },
            {
              "oid": "0535958813030292",
              "text": "邓泽鸣",
              "optionId": "25",
              "pageUrl": "",
              "picUrl": "https://u9.iqiyipic.com/feige/20210129/f5/1a/feige_1af54d94e124430f8e8797657e9ab040_default.jpg",
              "userCouldJoinTimes": 2,
              "userJoinTimes": 0,
              "todayHasJoined": false,
              "runTimes": 0,
              "showNum": 0,
              "kv": "{\"biaoshi\":\"dengzeming\",\"people_state\":\"1\",\"uid\":\"1676568515\"}",
              "canVote": 0
            },
            {
              "oid": "1404085321030095",
              "text": "何德瑞",
              "optionId": "31",
              "pageUrl": "",
              "picUrl": "https://u7.iqiyipic.com/feige/20210129/11/4b/feige_4b11d7aebe46456bbe0b95e3db4696f6_default.jpg",
              "userCouldJoinTimes": 2,
              "userJoinTimes": 0,
              "todayHasJoined": false,
              "runTimes": 0,
              "showNum": 0,
              "kv": "{\"biaoshi\":\"hederui\",\"people_state\":\"1\",\"uid\":\"1419659265975210\"}",
              "canVote": 0
            },
            {
              "oid": "1225203031030333",
              "text": "黄泓铭",
              "optionId": "33",
              "pageUrl": "",
              "picUrl": "https://u5.iqiyipic.com/feige/20210129/39/56/feige_5639a18ae7994240956567d14ddeb011_default.jpg",
              "userCouldJoinTimes": 2,
              "userJoinTimes": 0,
              "todayHasJoined": false,
              "runTimes": 0,
              "showNum": 0,
              "kv": "{\"biaoshi\":\"huanghongming\",\"people_state\":\"1\",\"uid\":\"1419551791273276\"}",
              "canVote": 0
            },
            {
              "oid": "0482947296030934",
              "text": "姜京佐",
              "optionId": "38",
              "pageUrl": "",
              "picUrl": "https://u5.iqiyipic.com/feige/20210129/d3/bc/feige_bcd332ad352941be9d607a0eca23a1a4_default.jpg",
              "userCouldJoinTimes": 2,
              "userJoinTimes": 0,
              "todayHasJoined": false,
              "runTimes": 0,
              "showNum": 0,
              "kv": "{\"biaoshi\":\"jiangjingzuo\",\"people_state\":\"1\",\"uid\":\"1493236446\"}",
              "canVote": 0
            },
            {
              "oid": "1108454306030004",
              "text": "刘冠佑",
              "optionId": "45",
              "pageUrl": "",
              "picUrl": "https://u8.iqiyipic.com/feige/20210129/0f/00/feige_000f028d724b4bd4b5d69ee6b29920a4_default.jpg",
              "userCouldJoinTimes": 2,
              "userJoinTimes": 0,
              "todayHasJoined": false,
              "runTimes": 0,
              "showNum": 0,
              "kv": "{\"biaoshi\":\"liuguanyou\",\"people_state\":\"1\",\"uid\":\"1395844477616595\"}",
              "canVote": 0
            },
            {
              "oid": "1336353286030192",
              "text": "连淮伟",
              "optionId": "48",
              "pageUrl": "",
              "picUrl": "https://u6.iqiyipic.com/feige/20210129/1b/17/feige_171ba1909fab4c24880a36bb06033688_default.jpg",
              "userCouldJoinTimes": 2,
              "userJoinTimes": 0,
              "todayHasJoined": false,
              "runTimes": 0,
              "showNum": 0,
              "kv": "{\"biaoshi\":\"lianhuaiwei\",\"people_state\":\"1\",\"uid\":\"1677611757\"}",
              "canVote": 0
            },
            {
              "oid": "0993621373030727",
              "text": "刘隽",
              "optionId": "49",
              "pageUrl": "",
              "picUrl": "https://u4.iqiyipic.com/feige/20210129/f8/06/feige_06f8f3247a094d4c906cd52357cd44ff_default.jpg",
              "userCouldJoinTimes": 2,
              "userJoinTimes": 0,
              "todayHasJoined": false,
              "runTimes": 0,
              "showNum": 0,
              "kv": "{\"biaoshi\":\"liujuan\",\"people_state\":\"1\",\"uid\":\"1419504747807212\"}",
              "canVote": 0
            },
            {
              "oid": "0351258412030320",
              "text": "李俊濠",
              "optionId": "50",
              "pageUrl": "",
              "picUrl": "https://u5.iqiyipic.com/feige/20210129/83/d0/feige_d08377eacf244956820e5e5296c1a466_default.jpg",
              "userCouldJoinTimes": 2,
              "userJoinTimes": 0,
              "todayHasJoined": false,
              "runTimes": 0,
              "showNum": 0,
              "kv": "{\"biaoshi\":\"lijunhao\",\"people_state\":\"1\",\"uid\":\"1419451631149965\"}",
              "canVote": 0
            },
            {
              "oid": "1279731398030707",
              "text": "李钦",
              "optionId": "53",
              "pageUrl": "",
              "picUrl": "https://u4.iqiyipic.com/feige/20210129/d4/b6/feige_b6d4821979024eb8a30cf8050937fb39_default.jpg",
              "userCouldJoinTimes": 2,
              "userJoinTimes": 0,
              "todayHasJoined": false,
              "runTimes": 0,
              "showNum": 0,
              "kv": "{\"biaoshi\":\"liqin\",\"people_state\":\"1\",\"uid\":\"1395859409347040\"}",
              "canVote": 0
            },
            {
              "oid": "1383727717030133",
              "text": "梁森",
              "optionId": "56",
              "pageUrl": "",
              "picUrl": "https://u9.iqiyipic.com/feige/20210129/d0/41/feige_41d0309aa8fb443782aec1b5ee0fd4c9_default.jpg",
              "userCouldJoinTimes": 2,
              "userJoinTimes": 0,
              "todayHasJoined": false,
              "runTimes": 0,
              "showNum": 0,
              "kv": "{\"biaoshi\":\"liangsen\",\"people_state\":\"1\",\"uid\":\"1419510653547817\"}",
              "canVote": 0
            },
            {
              "oid": "0881204904030116",
              "text": "罗一舟",
              "optionId": "62",
              "pageUrl": "",
              "picUrl": "https://u8.iqiyipic.com/feige/20210129/00/32/feige_3200365f351a42d0af66bff94172e727_default.jpg",
              "userCouldJoinTimes": 2,
              "userJoinTimes": 0,
              "todayHasJoined": false,
              "runTimes": 0,
              "showNum": 0,
              "kv": "{\"biaoshi\":\"luoyizhou\",\"people_state\":\"1\",\"uid\":\"1410679361774068\"}",
              "canVote": 0
            },
            {
              "oid": "0050418138030062",
              "text": "桥本裕太",
              "optionId": "67",
              "pageUrl": "",
              "picUrl": "https://u5.iqiyipic.com/feige/20210129/76/31/feige_3176f007156b41b2b89f60d331b045de_default.jpg",
              "userCouldJoinTimes": 2,
              "userJoinTimes": 0,
              "todayHasJoined": false,
              "runTimes": 0,
              "showNum": 0,
              "kv": "{\"biaoshi\":\"qiaobenyutai\",\"people_state\":\"1\",\"uid\":\"1419544040055737\"}",
              "canVote": 0
            },
            {
              "oid": "1566695626030311",
              "text": "邱丹枫",
              "optionId": "68",
              "pageUrl": "",
              "picUrl": "https://u9.iqiyipic.com/feige/20210129/a8/23/feige_23a852147e194ef4b408b8ae71f2de28_default.jpg",
              "userCouldJoinTimes": 2,
              "userJoinTimes": 0,
              "todayHasJoined": false,
              "runTimes": 0,
              "showNum": 0,
              "kv": "{\"biaoshi\":\"qiudanfeng\",\"people_state\":\"1\",\"uid\":\"1419509646754727\"}",
              "canVote": 0
            },
            {
              "oid": "1602793521030337",
              "text": "十七",
              "optionId": "71",
              "pageUrl": "",
              "picUrl": "https://u0.iqiyipic.com/feige/20210129/a7/07/feige_07a73887cbef4ce28047cbd4b37cb013_default.jpg",
              "userCouldJoinTimes": 2,
              "userJoinTimes": 0,
              "todayHasJoined": false,
              "runTimes": 0,
              "showNum": 0,
              "kv": "{\"biaoshi\":\"shiqi\",\"people_state\":\"1\",\"uid\":\"1416235506095412\"}",
              "canVote": 0
            },
            {
              "oid": "1352990527030252",
              "text": "孙亦航",
              "optionId": "74",
              "pageUrl": "",
              "picUrl": "https://u7.iqiyipic.com/feige/20210129/fd/f7/feige_f7fd5d41e79e46d59db6bb241536e9d2_default.jpg",
              "userCouldJoinTimes": 2,
              "userJoinTimes": 0,
              "todayHasJoined": false,
              "runTimes": 0,
              "showNum": 0,
              "kv": "{\"biaoshi\":\"sunyihang\",\"people_state\":\"1\",\"uid\":\"1416280166892014\"}",
              "canVote": 0
            },
            {
              "oid": "0125572415030337",
              "text": "孙滢皓",
              "optionId": "75",
              "pageUrl": "",
              "picUrl": "https://u1.iqiyipic.com/feige/20210129/cb/98/feige_98cb8315acc644bc8fa074c6d4a5a88c_default.jpg",
              "userCouldJoinTimes": 2,
              "userJoinTimes": 0,
              "todayHasJoined": false,
              "runTimes": 0,
              "showNum": 0,
              "kv": "{\"biaoshi\":\"sunyinghao\",\"people_state\":\"1\",\"uid\":\"1419507667203366\"}",
              "canVote": 0
            },
            {
              "oid": "0085447054030987",
              "text": "唐九洲",
              "optionId": "77",
              "pageUrl": "",
              "picUrl": "https://u0.iqiyipic.com/feige/20210129/f2/2c/feige_2cf210c07a2246259159a2a2a21d4d36_default.jpg",
              "userCouldJoinTimes": 2,
              "userJoinTimes": 0,
              "todayHasJoined": false,
              "runTimes": 0,
              "showNum": 0,
              "kv": "{\"biaoshi\":\"tangjiuzhou\",\"people_state\":\"1\",\"uid\":\"1413851128005560\"}",
              "canVote": 0
            },
            {
              "oid": "0632211846030402",
              "text": "汪佳辰",
              "optionId": "80",
              "pageUrl": "",
              "picUrl": "https://u7.iqiyipic.com/feige/20210129/8c/78/feige_788cebe6ea73462ca32ee07c12617311_default.jpg",
              "userCouldJoinTimes": 2,
              "userJoinTimes": 0,
              "todayHasJoined": false,
              "runTimes": 0,
              "showNum": 0,
              "kv": "{\"biaoshi\":\"wangjiachen\",\"people_state\":\"1\",\"uid\":\"1419550415397316\"}",
              "canVote": 0
            },
            {
              "oid": "1276232931030840",
              "text": "王南钧",
              "optionId": "82",
              "pageUrl": "",
              "picUrl": "https://u1.iqiyipic.com/feige/20210129/c5/e8/feige_e8c5008990eb431a88d2d9445d614e49_default.jpg",
              "userCouldJoinTimes": 2,
              "userJoinTimes": 0,
              "todayHasJoined": false,
              "runTimes": 0,
              "showNum": 0,
              "kv": "{\"biaoshi\":\"wangnanjun\",\"people_state\":\"1\",\"uid\":\"1395851356283801\"}",
              "canVote": 0
            },
            {
              "oid": "0417053195030052",
              "text": "徐新驰",
              "optionId": "90",
              "pageUrl": "",
              "picUrl": "https://u9.iqiyipic.com/feige/20210129/7e/fa/feige_fa7ebbaabd854dde9cdf8b2e2513260c_default.jpg",
              "userCouldJoinTimes": 2,
              "userJoinTimes": 0,
              "todayHasJoined": false,
              "runTimes": 0,
              "showNum": 0,
              "kv": "{\"biaoshi\":\"xuxinchi\",\"people_state\":\"1\",\"uid\":\"1419463039656407\"}",
              "canVote": 0
            },
            {
              "oid": "1563379228030164",
              "text": "徐子未",
              "optionId": "93",
              "pageUrl": "",
              "picUrl": "https://u5.iqiyipic.com/feige/20210129/a1/47/feige_47a1cdd1d91e461b8fe20e31a469874a_default.jpg",
              "userCouldJoinTimes": 2,
              "userJoinTimes": 0,
              "todayHasJoined": false,
              "runTimes": 0,
              "showNum": 0,
              "kv": "{\"biaoshi\":\"xuziwei\",\"people_state\":\"1\",\"uid\":\"1419506794788132\"}",
              "canVote": 0
            },
            {
              "oid": "1615794628030623",
              "text": "杨昊铭",
              "optionId": "97",
              "pageUrl": "",
              "picUrl": "https://u6.iqiyipic.com/feige/20210129/02/5a/feige_5a023b2fa3e4460d96d6a03e3883f746_default.jpg",
              "userCouldJoinTimes": 2,
              "userJoinTimes": 0,
              "todayHasJoined": false,
              "runTimes": 0,
              "showNum": 0,
              "kv": "{\"biaoshi\":\"yanghaoming\",\"people_state\":\"1\",\"uid\":\"1419502365442980\"}",
              "canVote": 0
            },
            {
              "oid": "0084199055030970",
              "text": "余景天",
              "optionId": "98",
              "pageUrl": "",
              "picUrl": "https://u9.iqiyipic.com/feige/20210129/b7/16/feige_16b789ccaad24c4b98040b8fa867c568_default.jpg",
              "userCouldJoinTimes": 2,
              "userJoinTimes": 0,
              "todayHasJoined": false,
              "runTimes": 0,
              "showNum": 0,
              "kv": "{\"biaoshi\":\"yujingtian\",\"people_state\":\"1\",\"uid\":\"1413663760217354\"}",
              "canVote": 0
            },
            {
              "oid": "0822841934030509",
              "text": "彦希",
              "optionId": "100",
              "pageUrl": "",
              "picUrl": "https://u6.iqiyipic.com/feige/20210129/90/1e/feige_1e90885a495241b9a6a065eba8449b0b_default.jpg",
              "userCouldJoinTimes": 2,
              "userJoinTimes": 0,
              "todayHasJoined": false,
              "runTimes": 0,
              "showNum": 0,
              "kv": "{\"biaoshi\":\"yanxi\",\"people_state\":\"1\",\"uid\":\"1452499384\"}",
              "canVote": 0
            },
            {
              "oid": "1490255510030097",
              "text": "亿轩",
              "optionId": "101",
              "pageUrl": "",
              "picUrl": "https://u0.iqiyipic.com/feige/20210129/ff/49/feige_49ff1554ec394f88b2b3e7de67b080d1_default.jpg",
              "userCouldJoinTimes": 2,
              "userJoinTimes": 0,
              "todayHasJoined": false,
              "runTimes": 0,
              "showNum": 0,
              "kv": "{\"biaoshi\":\"yixuan\",\"people_state\":\"1\",\"uid\":\"1419658997531125\"}",
              "canVote": 0
            },
            {
              "oid": "1378547891030964",
              "text": "张思源",
              "optionId": "113",
              "pageUrl": "",
              "picUrl": "https://u5.iqiyipic.com/feige/20210129/30/e7/feige_e7301faa93704afca557066bf6de9422_default.jpg",
              "userCouldJoinTimes": 2,
              "userJoinTimes": 0,
              "todayHasJoined": false,
              "runTimes": 0,
              "showNum": 0,
              "kv": "{\"biaoshi\":\"zhangsiyuan\",\"people_state\":\"1\",\"uid\":\"1419440457667840\"}",
              "canVote": 0
            },
            {
              "oid": "0451011405030706",
              "text": "郑星源",
              "optionId": "114",
              "pageUrl": "",
              "picUrl": "https://u3.iqiyipic.com/feige/20210129/6f/da/feige_da6fd77f3c304b03a7a0a37e5f36fb2a_default.jpg",
              "userCouldJoinTimes": 2,
              "userJoinTimes": 0,
              "todayHasJoined": false,
              "runTimes": 0,
              "showNum": 0,
              "kv": "{\"biaoshi\":\"zhengxingyuan\",\"people_state\":\"1\",\"uid\":\"1410329892356557\"}",
              "canVote": 0
            },
            {
              "oid": "1071315199030570",
              "text": "梓渝",
              "optionId": "116",
              "pageUrl": "",
              "picUrl": "https://u9.iqiyipic.com/feige/20210129/1d/f8/feige_f81d3fffc4754499b7e691e2390a76e3_default.jpg",
              "userCouldJoinTimes": 2,
              "userJoinTimes": 0,
              "todayHasJoined": false,
              "runTimes": 0,
              "showNum": 0,
              "kv": "{\"biaoshi\":\"ziyu\",\"people_state\":\"1\",\"uid\":\"1410287144170814\"}",
              "canVote": 0
            },
            {
              "oid": "0168688580030631",
              "text": "爱尔法·金",
              "optionId": "1",
              "pageUrl": "",
              "picUrl": "https://u6.iqiyipic.com/feige/20210129/70/96/feige_9670f9f025dc4632aca1a4b6adf85223_default.jpg",
              "userCouldJoinTimes": 2,
              "userJoinTimes": 0,
              "todayHasJoined": false,
              "runTimes": 0,
              "showNum": 0,
              "kv": "{\"biaoshi\":\"aierfajin\",\"people_state\":\"2\",\"uid\":\"1399547477631887\"}",
              "canVote": 1
            },
            {
              "oid": "1366185940030256",
              "text": "艾克里里",
              "optionId": "2",
              "pageUrl": "",
              "picUrl": "https://u9.iqiyipic.com/feige/20210129/e6/0a/feige_0ae6ebc0fcaa46e0927a864bd496deee_default.jpg",
              "userCouldJoinTimes": 2,
              "userJoinTimes": 0,
              "todayHasJoined": false,
              "runTimes": 0,
              "showNum": 0,
              "kv": "{\"biaoshi\":\"aikelili\",\"people_state\":\"2\",\"uid\":\"1416233291502899\"}",
              "canVote": 1
            },
            {
              "oid": "1360584090030455",
              "text": "艾力扎提",
              "optionId": "3",
              "pageUrl": "",
              "picUrl": "https://u4.iqiyipic.com/feige/20210129/38/32/feige_32385d3a195b4b3e9ce2024d2c17263e_default.jpg",
              "userCouldJoinTimes": 2,
              "userJoinTimes": 0,
              "todayHasJoined": false,
              "runTimes": 0,
              "showNum": 0,
              "kv": "{\"biaoshi\":\"ailizhati\",\"people_state\":\"2\",\"uid\":\"1413226881360345\"}",
              "canVote": 1
            },
            {
              "oid": "0409495050030035",
              "text": "阿煜",
              "optionId": "4",
              "pageUrl": "",
              "picUrl": "https://u1.iqiyipic.com/feige/20210129/24/dc/feige_dc24a6ed3c464bf38938f78b363353ae_default.jpg",
              "userCouldJoinTimes": 2,
              "userJoinTimes": 0,
              "todayHasJoined": false,
              "runTimes": 0,
              "showNum": 0,
              "kv": "{\"biaoshi\":\"ayu\",\"people_state\":\"2\",\"uid\":\"1419545046688192\"}",
              "canVote": 1
            },
            {
              "oid": "0894470242030274",
              "text": "白丁",
              "optionId": "5",
              "pageUrl": "",
              "picUrl": "https://u0.iqiyipic.com/feige/20210129/91/ba/feige_ba91b12c9111400781acb96929add37f_default.jpg",
              "userCouldJoinTimes": 2,
              "userJoinTimes": 0,
              "todayHasJoined": false,
              "runTimes": 0,
              "showNum": 0,
              "kv": "{\"biaoshi\":\"baiding\",\"people_state\":\"2\",\"uid\":\"1410672214672264\"}",
              "canVote": 1
            },
            {
              "oid": "0069183184030274",
              "text": "包涵",
              "optionId": "6",
              "pageUrl": "",
              "picUrl": "https://u1.iqiyipic.com/feige/20210129/1c/38/feige_381c682e588c4d66aa0b965f35453d00_default.jpg",
              "userCouldJoinTimes": 2,
              "userJoinTimes": 0,
              "todayHasJoined": false,
              "runTimes": 0,
              "showNum": 0,
              "kv": "{\"biaoshi\":\"baohan\",\"people_state\":\"2\",\"uid\":\"1416248122409906\"}",
              "canVote": 1
            },
            {
              "oid": "0910985390030818",
              "text": "白陆",
              "optionId": "7",
              "pageUrl": "",
              "picUrl": "https://u5.iqiyipic.com/feige/20210129/92/8c/feige_8c9279b61fa14711a84e827874c09460_default.jpg",
              "userCouldJoinTimes": 2,
              "userJoinTimes": 0,
              "todayHasJoined": false,
              "runTimes": 0,
              "showNum": 0,
              "kv": "{\"biaoshi\":\"bailu\",\"people_state\":\"2\",\"uid\":\"1416283321169173\"}",
              "canVote": 1
            },
            {
              "oid": "0525341039030507",
              "text": "陈鼎鼎",
              "optionId": "8",
              "pageUrl": "",
              "picUrl": "https://u9.iqiyipic.com/feige/20210129/d7/26/feige_26d70a462ff541f3b19f07f87f223c77_default.jpg",
              "userCouldJoinTimes": 2,
              "userJoinTimes": 0,
              "todayHasJoined": false,
              "runTimes": 0,
              "showNum": 0,
              "kv": "{\"biaoshi\":\"chendingding\",\"people_state\":\"2\",\"uid\":\"1410260669715757\"}",
              "canVote": 1
            },
            {
              "oid": "1613458014030592",
              "text": "蔡飞扬",
              "optionId": "9",
              "pageUrl": "",
              "picUrl": "https://u1.iqiyipic.com/feige/20210129/3b/1c/feige_1c3b355d28144d7f9a3c03db4c382f1a_default.jpg",
              "userCouldJoinTimes": 2,
              "userJoinTimes": 0,
              "todayHasJoined": false,
              "runTimes": 0,
              "showNum": 0,
              "kv": "{\"biaoshi\":\"caifeiyang\",\"people_state\":\"2\",\"uid\":\"1410669161379110\"}",
              "canVote": 1
            },
            {
              "oid": "0971182626030875",
              "text": "陈金鑫",
              "optionId": "12",
              "pageUrl": "",
              "picUrl": "https://u0.iqiyipic.com/feige/20210129/4d/55/feige_554d13aa6fee410480a101de2ccf8cc0_default.jpg",
              "userCouldJoinTimes": 2,
              "userJoinTimes": 0,
              "todayHasJoined": false,
              "runTimes": 0,
              "showNum": 0,
              "kv": "{\"biaoshi\":\"chenjinxin\",\"people_state\":\"2\",\"uid\":\"1419648931353889\"}",
              "canVote": 1
            },
            {
              "oid": "1330597964030597",
              "text": "陈建宇 ",
              "optionId": "13",
              "pageUrl": "",
              "picUrl": "https://u1.iqiyipic.com/feige/20210129/93/fb/feige_fb938de70921427092360d42c405297b_default.jpg",
              "userCouldJoinTimes": 2,
              "userJoinTimes": 0,
              "todayHasJoined": false,
              "runTimes": 0,
              "showNum": 0,
              "kv": "{\"biaoshi\":\"chenjianyu\",\"people_state\":\"2\",\"uid\":\"1410682079683469\"}",
              "canVote": 1
            },
            {
              "oid": "0406855615030720",
              "text": "陈俊宇",
              "optionId": "14",
              "pageUrl": "",
              "picUrl": "https://u5.iqiyipic.com/feige/20210129/6a/6c/feige_6c6adbad1b0a45e1a2995b99fe9650bd_default.jpg",
              "userCouldJoinTimes": 2,
              "userJoinTimes": 0,
              "todayHasJoined": false,
              "runTimes": 0,
              "showNum": 0,
              "kv": "{\"biaoshi\":\"chenjunyu\",\"people_state\":\"2\",\"uid\":\"1410675939214220\"}",
              "canVote": 1
            },
            {
              "oid": "0226012983030226",
              "text": "陈泫孝",
              "optionId": "15",
              "pageUrl": "",
              "picUrl": "https://u3.iqiyipic.com/feige/20210129/58/9d/feige_9d58dd101880469793d07df3e32a7799_default.jpg",
              "userCouldJoinTimes": 2,
              "userJoinTimes": 0,
              "todayHasJoined": false,
              "runTimes": 0,
              "showNum": 0,
              "kv": "{\"biaoshi\":\"chenxuanxiao\",\"people_state\":\"2\",\"uid\":\"1413311404966349\"}",
              "canVote": 1
            },
            {
              "oid": "0815125559030549",
              "text": "崔云峰",
              "optionId": "17",
              "pageUrl": "",
              "picUrl": "https://u1.iqiyipic.com/feige/20210129/ca/fc/feige_fcca5171215641feb25e4cd5b735b3ec_default.jpg",
              "userCouldJoinTimes": 2,
              "userJoinTimes": 0,
              "todayHasJoined": false,
              "runTimes": 0,
              "showNum": 0,
              "kv": "{\"biaoshi\":\"cuiyunfeng\",\"people_state\":\"2\",\"uid\":\"1410256609485287\"}",
              "canVote": 1
            },
            {
              "oid": "1388958665030494",
              "text": "曹宇雪",
              "optionId": "19",
              "pageUrl": "",
              "picUrl": "https://u7.iqiyipic.com/feige/20210129/8f/ff/feige_ff8f8f0fe3b8461182295283c803cad1_default.jpg",
              "userCouldJoinTimes": 2,
              "userJoinTimes": 0,
              "todayHasJoined": false,
              "runTimes": 0,
              "showNum": 0,
              "kv": "{\"biaoshi\":\"caoyuxue\",\"people_state\":\"2\",\"uid\":\"1410673623958409\"}",
              "canVote": 1
            },
            {
              "oid": "0848116042030255",
              "text": "曹子俊",
              "optionId": "20",
              "pageUrl": "",
              "picUrl": "https://u6.iqiyipic.com/feige/20210129/14/8d/feige_8d14daf57bbc42c48789b51364e3f701_default.jpg",
              "userCouldJoinTimes": 2,
              "userJoinTimes": 0,
              "todayHasJoined": false,
              "runTimes": 0,
              "showNum": 0,
              "kv": "{\"biaoshi\":\"caozijun\",\"people_state\":\"2\",\"uid\":\"1416289327260149\"}",
              "canVote": 1
            },
            {
              "oid": "0392254145030560",
              "text": "陈子龙",
              "optionId": "21",
              "pageUrl": "",
              "picUrl": "https://u3.iqiyipic.com/feige/20210129/61/09/feige_09611bc1a7f44e50bd4da879e622c46d_default.jpg",
              "userCouldJoinTimes": 2,
              "userJoinTimes": 0,
              "todayHasJoined": false,
              "runTimes": 0,
              "showNum": 0,
              "kv": "{\"biaoshi\":\"chenzilong\",\"people_state\":\"2\",\"uid\":\"1419658058007027\"}",
              "canVote": 1
            },
            {
              "oid": "1228761855030610",
              "text": "冯陈思楠",
              "optionId": "26",
              "pageUrl": "",
              "picUrl": "https://u8.iqiyipic.com/feige/20210129/43/66/feige_66434ffffe08463591ba7c1e13e6c4ac_default.jpg",
              "userCouldJoinTimes": 2,
              "userJoinTimes": 0,
              "todayHasJoined": false,
              "runTimes": 0,
              "showNum": 0,
              "kv": "{\"biaoshi\":\"fengchensinan\",\"people_state\":\"2\",\"uid\":\"1399498857403671\"}",
              "canVote": 1
            },
            {
              "oid": "0900616200030868",
              "text": "付雪岩",
              "optionId": "27",
              "pageUrl": "",
              "picUrl": "https://u5.iqiyipic.com/feige/20210129/2b/4c/feige_4c2bcfe4d60d4e54ba52838240dc0dd5_default.jpg",
              "userCouldJoinTimes": 2,
              "userJoinTimes": 0,
              "todayHasJoined": false,
              "runTimes": 0,
              "showNum": 0,
              "kv": "{\"biaoshi\":\"fuxueyan\",\"people_state\":\"2\",\"uid\":\"1410663087866753\"}",
              "canVote": 1
            },
            {
              "oid": "0703927581030544",
              "text": "方政",
              "optionId": "28",
              "pageUrl": "",
              "picUrl": "https://u3.iqiyipic.com/feige/20210129/44/80/feige_80441c7c0f524e9ea03d30b0b8121ab5_default.jpg",
              "userCouldJoinTimes": 2,
              "userJoinTimes": 0,
              "todayHasJoined": false,
              "runTimes": 0,
              "showNum": 0,
              "kv": "{\"biaoshi\":\"fangzheng\",\"people_state\":\"2\",\"uid\":\"1410666745451810\"}",
              "canVote": 1
            },
            {
              "oid": "0501327278030167",
              "text": "高一百",
              "optionId": "29",
              "pageUrl": "",
              "picUrl": "https://u5.iqiyipic.com/feige/20210129/43/a1/feige_a1439b27663d4e798dd1c5d82fd2ff24_default.jpg",
              "userCouldJoinTimes": 2,
              "userJoinTimes": 0,
              "todayHasJoined": false,
              "runTimes": 0,
              "showNum": 0,
              "kv": "{\"biaoshi\":\"gaoyibai\",\"people_state\":\"2\",\"uid\":\"1419470757176211\"}",
              "canVote": 1
            },
            {
              "oid": "1390784428030697",
              "text": "龚毅星",
              "optionId": "30",
              "pageUrl": "",
              "picUrl": "https://u1.iqiyipic.com/feige/20210129/2c/b5/feige_b52c6a2df62743cc8f106f1c65188563_default.jpg",
              "userCouldJoinTimes": 2,
              "userJoinTimes": 0,
              "todayHasJoined": false,
              "runTimes": 0,
              "showNum": 0,
              "kv": "{\"biaoshi\":\"gongyixing\",\"people_state\":\"2\",\"uid\":\"1419657017820072\"}",
              "canVote": 1
            },
            {
              "oid": "0544965797030544",
              "text": "黄河",
              "optionId": "32",
              "pageUrl": "",
              "picUrl": "https://u8.iqiyipic.com/feige/20210129/af/e5/feige_e5af1d72264f419f86a8674ccb24899c_default.jpg",
              "userCouldJoinTimes": 2,
              "userJoinTimes": 0,
              "todayHasJoined": false,
              "runTimes": 0,
              "showNum": 0,
              "kv": "{\"biaoshi\":\"huanghe\",\"people_state\":\"2\",\"uid\":\"1413259127161729\"}",
              "canVote": 1
            },
            {
              "oid": "0194754043030318",
              "text": "韩竞德",
              "optionId": "34",
              "pageUrl": "",
              "picUrl": "https://u7.iqiyipic.com/feige/20210129/7b/5c/feige_5c7bb371d55849df80d1df8c83ce900f_default.jpg",
              "userCouldJoinTimes": 2,
              "userJoinTimes": 0,
              "todayHasJoined": false,
              "runTimes": 0,
              "showNum": 0,
              "kv": "{\"biaoshi\":\"hanjingde\",\"people_state\":\"2\",\"uid\":\"1419553670169031\"}",
              "canVote": 1
            },
            {
              "oid": "0840130902030688",
              "text": "黄鉴曦",
              "optionId": "35",
              "pageUrl": "",
              "picUrl": "https://u0.iqiyipic.com/feige/20210129/1d/63/feige_631d7ef131bb4f8e9590212e9ac2e92e_default.jpg",
              "userCouldJoinTimes": 2,
              "userJoinTimes": 0,
              "todayHasJoined": false,
              "runTimes": 0,
              "showNum": 0,
              "kv": "{\"biaoshi\":\"huangjianxi\",\"people_state\":\"2\",\"uid\":\"1410664195170788\"}",
              "canVote": 1
            },
            {
              "oid": "1380417932030469",
              "text": "韩瑞泽",
              "optionId": "36",
              "pageUrl": "",
              "picUrl": "https://u3.iqiyipic.com/feige/20210129/fe/ce/feige_cefe80fb90014b2283596d13db3e13a8_default.jpg",
              "userCouldJoinTimes": 2,
              "userJoinTimes": 0,
              "todayHasJoined": false,
              "runTimes": 0,
              "showNum": 0,
              "kv": "{\"biaoshi\":\"hanruize\",\"people_state\":\"2\",\"uid\":\"1410340797699353\"}",
              "canVote": 1
            },
            {
              "oid": "0163450656030334",
              "text": "胡轩豪",
              "optionId": "37",
              "pageUrl": "",
              "picUrl": "https://u5.iqiyipic.com/feige/20210129/91/0d/feige_0d913e87658040e1bb4d997d73df3b56_default.jpg",
              "userCouldJoinTimes": 2,
              "userJoinTimes": 0,
              "todayHasJoined": false,
              "runTimes": 0,
              "showNum": 0,
              "kv": "{\"biaoshi\":\"huxuanhao\",\"people_state\":\"2\",\"uid\":\"1419655138923815\"}",
              "canVote": 1
            },
            {
              "oid": "1320265094030982",
              "text": "蒋智豪",
              "optionId": "39",
              "pageUrl": "",
              "picUrl": "https://u8.iqiyipic.com/feige/20210129/57/27/feige_275799ac81f84bc9a058abbe09e44ef9_default.jpg",
              "userCouldJoinTimes": 2,
              "userJoinTimes": 0,
              "todayHasJoined": false,
              "runTimes": 0,
              "showNum": 0,
              "kv": "{\"biaoshi\":\"jiangzhihao\",\"people_state\":\"2\",\"uid\":\"1410886761718261\"}",
              "canVote": 1
            },
            {
              "oid": "0099039735030721",
              "text": "柯尔",
              "optionId": "40",
              "pageUrl": "",
              "picUrl": "https://u5.iqiyipic.com/feige/20210129/ff/46/feige_46ff3351a9334cfb9355c98e4e4a960f_default.jpg",
              "userCouldJoinTimes": 2,
              "userJoinTimes": 0,
              "todayHasJoined": false,
              "runTimes": 0,
              "showNum": 0,
              "kv": "{\"biaoshi\":\"keer\",\"people_state\":\"2\",\"uid\":\"1416243827594554\"}",
              "canVote": 1
            },
            {
              "oid": "0921235081030140",
              "text": "苛尔力钧",
              "optionId": "41",
              "pageUrl": "",
              "picUrl": "https://u4.iqiyipic.com/feige/20210129/9e/3f/feige_3f9e82e39c18453f8d5db7f3e3a770ea_default.jpg",
              "userCouldJoinTimes": 2,
              "userJoinTimes": 0,
              "todayHasJoined": false,
              "runTimes": 0,
              "showNum": 0,
              "kv": "{\"biaoshi\":\"keerlijun\",\"people_state\":\"2\",\"uid\":\"1413866898596318\"}",
              "canVote": 1
            },
            {
              "oid": "1118526846030385",
              "text": "卡斯",
              "optionId": "42",
              "pageUrl": "",
              "picUrl": "https://u6.iqiyipic.com/feige/20210129/ff/57/feige_57ff356c837e4cc09e46e485b36e928c_default.jpg",
              "userCouldJoinTimes": 2,
              "userJoinTimes": 0,
              "todayHasJoined": false,
              "runTimes": 0,
              "showNum": 0,
              "kv": "{\"biaoshi\":\"kasi\",\"people_state\":\"2\",\"uid\":\"1410268521452849\"}",
              "canVote": 1
            },
            {
              "oid": "0178548572030909",
              "text": "孔祥池",
              "optionId": "43",
              "pageUrl": "",
              "picUrl": "https://u8.iqiyipic.com/feige/20210129/62/f4/feige_f462a8bbb2ce4587a755e61721ede43a_default.jpg",
              "userCouldJoinTimes": 2,
              "userJoinTimes": 0,
              "todayHasJoined": false,
              "runTimes": 0,
              "showNum": 0,
              "kv": "{\"biaoshi\":\"kongxiangchi\",\"people_state\":\"2\",\"uid\":\"1410881393153313\"}",
              "canVote": 1
            },
            {
              "oid": "1183942899030642",
              "text": "刘峰磊",
              "optionId": "44",
              "pageUrl": "",
              "picUrl": "https://u1.iqiyipic.com/feige/20210129/72/87/feige_8772958f82ba429e900ca14a27c1026c_default.jpg",
              "userCouldJoinTimes": 2,
              "userJoinTimes": 0,
              "todayHasJoined": false,
              "runTimes": 0,
              "showNum": 0,
              "kv": "{\"biaoshi\":\"liufenglei\",\"people_state\":\"2\",\"uid\":\"1413829686723009\"}",
              "canVote": 1
            },
            {
              "oid": "0985624578030992",
              "text": "李昊霖",
              "optionId": "46",
              "pageUrl": "",
              "picUrl": "https://u4.iqiyipic.com/feige/20210129/70/b2/feige_b270b27d45144cda94ad4c5b41905917_default.jpg",
              "userCouldJoinTimes": 2,
              "userJoinTimes": 0,
              "todayHasJoined": false,
              "runTimes": 0,
              "showNum": 0,
              "kv": "{\"biaoshi\":\"lihaolin\",\"people_state\":\"2\",\"uid\":\"1413243289469874\"}",
              "canVote": 1
            },
            {
              "oid": "0179493865030902",
              "text": "梁弘立",
              "optionId": "47",
              "pageUrl": "",
              "picUrl": "https://u5.iqiyipic.com/feige/20210129/ed/2c/feige_2ced6f8d386d4085a5f5330dfbb8127c_default.jpg",
              "userCouldJoinTimes": 2,
              "userJoinTimes": 0,
              "todayHasJoined": false,
              "runTimes": 0,
              "showNum": 0,
              "kv": "{\"biaoshi\":\"lianghongli\",\"people_state\":\"2\",\"uid\":\"1416282347930506\"}",
              "canVote": 1
            },
            {
              "oid": "1149951725030350",
              "text": "刘俊昊",
              "optionId": "51",
              "pageUrl": "",
              "picUrl": "https://u1.iqiyipic.com/feige/20210129/74/21/feige_2174b7657e124882af94293449fa9e99_default.jpg",
              "userCouldJoinTimes": 2,
              "userJoinTimes": 0,
              "todayHasJoined": false,
              "runTimes": 0,
              "showNum": 0,
              "kv": "{\"biaoshi\":\"liujunhao\",\"people_state\":\"2\",\"uid\":\"1395819244684162\"}",
              "canVote": 1
            },
            {
              "oid": "1583289784030001",
              "text": "黎明旭",
              "optionId": "52",
              "pageUrl": "",
              "picUrl": "https://u0.iqiyipic.com/feige/20210129/cb/6f/feige_6fcb79dc54f94d9b9c11b43c6ee2c2cf_default.jpg",
              "userCouldJoinTimes": 2,
              "userJoinTimes": 0,
              "todayHasJoined": false,
              "runTimes": 0,
              "showNum": 0,
              "kv": "{\"biaoshi\":\"limingxu\",\"people_state\":\"2\",\"uid\":\"1410322074182579\"}",
              "canVote": 1
            },
            {
              "oid": "1249798862030114",
              "text": "刘琦",
              "optionId": "54",
              "pageUrl": "",
              "picUrl": "https://u8.iqiyipic.com/feige/20210129/0c/ba/feige_ba0cc3ea88ad476f8bf9c6d9f30d1c67_default.jpg",
              "userCouldJoinTimes": 2,
              "userJoinTimes": 0,
              "todayHasJoined": false,
              "runTimes": 0,
              "showNum": 0,
              "kv": "{\"biaoshi\":\"liuqi\",\"people_state\":\"2\",\"uid\":\"1413856765310208\"}",
              "canVote": 1
            },
            {
              "oid": "0569109010030110",
              "text": "李硕",
              "optionId": "55",
              "pageUrl": "",
              "picUrl": "https://u4.iqiyipic.com/feige/20210129/50/ea/feige_ea500df255d14d43b74eb97a85085b42_default.jpg",
              "userCouldJoinTimes": 2,
              "userJoinTimes": 0,
              "todayHasJoined": false,
              "runTimes": 0,
              "showNum": 0,
              "kv": "{\"biaoshi\":\"lishuo\",\"people_state\":\"2\",\"uid\":\"1395856389448607\"}",
              "canVote": 1
            },
            {
              "oid": "0914711067030424",
              "text": "李天琪",
              "optionId": "57",
              "pageUrl": "",
              "picUrl": "https://u0.iqiyipic.com/feige/20210129/c1/2d/feige_2dc119eca57e402a876302c826b45f66_default.jpg",
              "userCouldJoinTimes": 2,
              "userJoinTimes": 0,
              "todayHasJoined": false,
              "runTimes": 0,
              "showNum": 0,
              "kv": "{\"biaoshi\":\"litianqi\",\"people_state\":\"2\",\"uid\":\"1410670201414124\"}",
              "canVote": 1
            },
            {
              "oid": "1280951752030288",
              "text": "李添翼",
              "optionId": "58",
              "pageUrl": "",
              "picUrl": "https://u0.iqiyipic.com/feige/20210129/5a/b4/feige_b45ab079180346dc95c4880109fde062_default.jpg",
              "userCouldJoinTimes": 2,
              "userJoinTimes": 0,
              "todayHasJoined": false,
              "runTimes": 0,
              "showNum": 0,
              "kv": "{\"biaoshi\":\"litianyi\",\"people_state\":\"2\",\"uid\":\"1395847833059799\"}",
              "canVote": 1
            },
            {
              "oid": "0424090066030401",
              "text": "刘欣",
              "optionId": "59",
              "pageUrl": "",
              "picUrl": "https://u7.iqiyipic.com/feige/20210129/5d/c7/feige_c75d615bac384b8da79ef5117d489d6e_default.jpg",
              "userCouldJoinTimes": 2,
              "userJoinTimes": 0,
              "todayHasJoined": false,
              "runTimes": 0,
              "showNum": 0,
              "kv": "{\"biaoshi\":\"liuxin\",\"people_state\":\"2\",\"uid\":\"1399482583352234\"}",
              "canVote": 1
            },
            {
              "oid": "0067296350030542",
              "text": "李远",
              "optionId": "60",
              "pageUrl": "",
              "picUrl": "https://u7.iqiyipic.com/feige/20210129/40/49/feige_4940263a3a3f4128b81bf680d437fcbe_default.jpg",
              "userCouldJoinTimes": 2,
              "userJoinTimes": 0,
              "todayHasJoined": false,
              "runTimes": 0,
              "showNum": 0,
              "kv": "{\"biaoshi\":\"liyuan\",\"people_state\":\"2\",\"uid\":\"1413233256694237\"}",
              "canVote": 1
            },
            {
              "oid": "1568039370030697",
              "text": "麟壹铭",
              "optionId": "61",
              "pageUrl": "",
              "picUrl": "https://u7.iqiyipic.com/feige/20210129/68/b3/feige_b368bd7ad34e404194896fa254f2408b_default.jpg",
              "userCouldJoinTimes": 2,
              "userJoinTimes": 0,
              "todayHasJoined": false,
              "runTimes": 0,
              "showNum": 0,
              "kv": "{\"biaoshi\":\"linyiming\",\"people_state\":\"2\",\"uid\":\"1399473792099237\"}",
              "canVote": 1
            },
            {
              "oid": "1592176726030432",
              "text": "李子晨",
              "optionId": "63",
              "pageUrl": "",
              "picUrl": "https://u2.iqiyipic.com/feige/20210129/ac/87/feige_87acc2f9aec84121a1a1e0229cad1f0b_default.jpg",
              "userCouldJoinTimes": 2,
              "userJoinTimes": 0,
              "todayHasJoined": false,
              "runTimes": 0,
              "showNum": 0,
              "kv": "{\"biaoshi\":\"lizichen\",\"people_state\":\"2\",\"uid\":\"1410671946388776\"}",
              "canVote": 1
            },
            {
              "oid": "0605268162030275",
              "text": "木森",
              "optionId": "64",
              "pageUrl": "",
              "picUrl": "https://u9.iqiyipic.com/feige/20210129/25/b1/feige_b125240542e649a0aa28ff38b81ad3bc_default.jpg",
              "userCouldJoinTimes": 2,
              "userJoinTimes": 0,
              "todayHasJoined": false,
              "runTimes": 0,
              "showNum": 0,
              "kv": "{\"biaoshi\":\"musen\",\"people_state\":\"2\",\"uid\":\"1413159034299267\"}",
              "canVote": 1
            },
            {
              "oid": "0471509204030860",
              "text": "马思涵",
              "optionId": "65",
              "pageUrl": "",
              "picUrl": "https://u1.iqiyipic.com/feige/20210129/10/7d/feige_7d109f93833e4baf85235515a37c0d27_default.jpg",
              "userCouldJoinTimes": 2,
              "userJoinTimes": 0,
              "todayHasJoined": false,
              "runTimes": 0,
              "showNum": 0,
              "kv": "{\"biaoshi\":\"masihan\",\"people_state\":\"2\",\"uid\":\"1399494193185260\"}",
              "canVote": 1
            },
            {
              "oid": "0984662706030941",
              "text": "牛在在",
              "optionId": "66",
              "pageUrl": "",
              "picUrl": "https://u1.iqiyipic.com/feige/20210129/ed/45/feige_45ed2243ff944a989e546ddef59571e9_default.jpg",
              "userCouldJoinTimes": 2,
              "userJoinTimes": 0,
              "todayHasJoined": false,
              "runTimes": 0,
              "showNum": 0,
              "kv": "{\"biaoshi\":\"niuzaizai\",\"people_state\":\"2\",\"uid\":\"1419656145413031\"}",
              "canVote": 1
            },
            {
              "oid": "1339688929030330",
              "text": "七哈",
              "optionId": "69",
              "pageUrl": "",
              "picUrl": "https://u0.iqiyipic.com/feige/20210129/3e/b5/feige_b53e9840cdc14c6fa98ab198fbac8495_default.jpg",
              "userCouldJoinTimes": 2,
              "userJoinTimes": 0,
              "todayHasJoined": false,
              "runTimes": 0,
              "showNum": 0,
              "kv": "{\"biaoshi\":\"qiha\",\"people_state\":\"2\",\"uid\":\"1410258018923819\"}",
              "canVote": 1
            },
            {
              "oid": "1292566984030686",
              "text": "时安",
              "optionId": "70",
              "pageUrl": "",
              "picUrl": "https://u3.iqiyipic.com/feige/20210129/07/83/feige_8307678b32fe492ca6c7348b997ffc99_default.jpg",
              "userCouldJoinTimes": 2,
              "userJoinTimes": 0,
              "todayHasJoined": false,
              "runTimes": 0,
              "showNum": 0,
              "kv": "{\"biaoshi\":\"shian\",\"people_state\":\"2\",\"uid\":\"1416224030327240\"}",
              "canVote": 1
            },
            {
              "oid": "0725983029030471",
              "text": "时尚",
              "optionId": "73",
              "pageUrl": "",
              "picUrl": "https://u1.iqiyipic.com/feige/20210129/13/72/feige_7213f762410f4553ab801b736ec63d96_default.jpg",
              "userCouldJoinTimes": 2,
              "userJoinTimes": 0,
              "todayHasJoined": false,
              "runTimes": 0,
              "showNum": 0,
              "kv": "{\"biaoshi\":\"shishang\",\"people_state\":\"2\",\"uid\":\"1411008832886056\"}",
              "canVote": 1
            },
            {
              "oid": "1075754181030006",
              "text": "十七君",
              "optionId": "72",
              "pageUrl": "",
              "picUrl": "https://u9.iqiyipic.com/feige/20210129/ca/d8/feige_d8ca3af6e21148cebe8c747c8c00d74b_default.jpg",
              "userCouldJoinTimes": 2,
              "userJoinTimes": 0,
              "todayHasJoined": false,
              "runTimes": 0,
              "showNum": 0,
              "kv": "{\"biaoshi\":\"shiqijun\",\"people_state\":\"2\",\"uid\":\"1410265434292714\"}",
              "canVote": 1
            },
            {
              "oid": "1141663503030083",
              "text": "唐嘉齐",
              "optionId": "76",
              "pageUrl": "",
              "picUrl": "https://u6.iqiyipic.com/feige/20210129/d5/99/feige_99d575c7821d4c3d9219e51cf9706497_default.jpg",
              "userCouldJoinTimes": 2,
              "userJoinTimes": 0,
              "todayHasJoined": false,
              "runTimes": 0,
              "showNum": 0,
              "kv": "{\"biaoshi\":\"tangjiaqi\",\"people_state\":\"2\",\"uid\":\"1410664631370213\"}",
              "canVote": 1
            },
            {
              "oid": "0549457044030694",
              "text": "王浩轩",
              "optionId": "78",
              "pageUrl": "",
              "picUrl": "https://u3.iqiyipic.com/feige/20210129/a0/6d/feige_6da03ea7f7744b21b373ea057d4e6e42_default.jpg",
              "userCouldJoinTimes": 2,
              "userJoinTimes": 0,
              "todayHasJoined": false,
              "runTimes": 0,
              "showNum": 0,
              "kv": "{\"biaoshi\":\"wanghaoxuan\",\"people_state\":\"2\",\"uid\":\"975742854767099\"}",
              "canVote": 1
            },
            {
              "oid": "0851348056030126",
              "text": "魏宏宇",
              "optionId": "79",
              "pageUrl": "",
              "picUrl": "https://u3.iqiyipic.com/feige/20210129/b0/53/feige_53b0533166634292af38d42fcc4e58d0_default.jpg",
              "userCouldJoinTimes": 2,
              "userJoinTimes": 0,
              "todayHasJoined": false,
              "runTimes": 0,
              "showNum": 0,
              "kv": "{\"biaoshi\":\"weihongyu\",\"people_state\":\"2\",\"uid\":\"1416287884411793\"}",
              "canVote": 1
            },
            {
              "oid": "1245838807030138",
              "text": "武悦",
              "optionId": "84",
              "pageUrl": "",
              "picUrl": "https://u8.iqiyipic.com/feige/20210129/96/57/feige_5796dee467d94a7a910b2486725a31ce_default.jpg",
              "userCouldJoinTimes": 2,
              "userJoinTimes": 0,
              "todayHasJoined": false,
              "runTimes": 0,
              "showNum": 0,
              "kv": "{\"biaoshi\":\"wuyue\",\"people_state\":\"2\",\"uid\":\"1419548234511675\"}",
              "canVote": 1
            },
            {
              "oid": "1232794603030369",
              "text": "王琳凯",
              "optionId": "81",
              "pageUrl": "",
              "picUrl": "https://u6.iqiyipic.com/feige/20210129/f1/63/feige_63f131ad8c864c4eb5844925274a8eae_default.jpg",
              "userCouldJoinTimes": 2,
              "userJoinTimes": 0,
              "todayHasJoined": false,
              "runTimes": 0,
              "showNum": 0,
              "kv": "{\"biaoshi\":\"wanglinkai\",\"people_state\":\"2\",\"uid\":\"1410665403274529\"}",
              "canVote": 1
            },
            {
              "oid": "0817727651030341",
              "text": "魏星丞",
              "optionId": "83",
              "pageUrl": "",
              "picUrl": "https://u0.iqiyipic.com/feige/20210129/67/2d/feige_2d6773cebad84a96b3cee8999e06dba7_default.jpg",
              "userCouldJoinTimes": 2,
              "userJoinTimes": 0,
              "todayHasJoined": false,
              "runTimes": 0,
              "showNum": 0,
              "kv": "{\"biaoshi\":\"weixingcheng\",\"people_state\":\"2\",\"uid\":\"1416215675426082\"}",
              "canVote": 1
            },
            {
              "oid": "0990393892030539",
              "text": "万禹辰",
              "optionId": "85",
              "pageUrl": "",
              "picUrl": "https://u8.iqiyipic.com/feige/20210129/9a/88/feige_889aeceb0e8048619a008ea8e06d3dbc_default.jpg",
              "userCouldJoinTimes": 2,
              "userJoinTimes": 0,
              "todayHasJoined": false,
              "runTimes": 0,
              "showNum": 0,
              "kv": "{\"biaoshi\":\"wanyuchen\",\"people_state\":\"2\",\"uid\":\"1399467148321699\"}",
              "canVote": 1
            },
            {
              "oid": "1117622076030739",
              "text": "徐滨",
              "optionId": "87",
              "pageUrl": "",
              "picUrl": "https://u4.iqiyipic.com/feige/20210129/d7/ae/feige_aed7ebe92cba4cb78a1c3242ca38fc6f_default.jpg",
              "userCouldJoinTimes": 2,
              "userJoinTimes": 0,
              "todayHasJoined": false,
              "runTimes": 0,
              "showNum": 0,
              "kv": "{\"biaoshi\":\"xubin\",\"people_state\":\"2\",\"uid\":\"1416285401543959\"}",
              "canVote": 1
            },
            {
              "oid": "0030949076030598",
              "text": "小河",
              "optionId": "88",
              "pageUrl": "",
              "picUrl": "https://u7.iqiyipic.com/feige/20210129/00/d3/feige_d3006407350f479898ce2a8964709f61_default.jpg",
              "userCouldJoinTimes": 2,
              "userJoinTimes": 0,
              "todayHasJoined": false,
              "runTimes": 0,
              "showNum": 0,
              "kv": "{\"biaoshi\":\"xiaohe\",\"people_state\":\"2\",\"uid\":\"1416227352368428\"}",
              "canVote": 1
            },
            {
              "oid": "0289821185030574",
              "text": "宣淏",
              "optionId": "89",
              "pageUrl": "",
              "picUrl": "https://u6.iqiyipic.com/feige/20210129/ac/ab/feige_abac4eb7afb3409fa45b958de17358d2_default.jpg",
              "userCouldJoinTimes": 2,
              "userJoinTimes": 0,
              "todayHasJoined": false,
              "runTimes": 0,
              "showNum": 0,
              "kv": "{\"biaoshi\":\"xuanhao\",\"people_state\":\"2\",\"uid\":\"1410667919712746\"}",
              "canVote": 1
            },
            {
              "oid": "0250036526030839",
              "text": "熊艺文",
              "optionId": "91",
              "pageUrl": "",
              "picUrl": "https://u2.iqiyipic.com/feige/20210129/3e/84/feige_843ee7291cf64e64b6297fa4039eb973_default.jpg",
              "userCouldJoinTimes": 2,
              "userJoinTimes": 0,
              "todayHasJoined": false,
              "runTimes": 0,
              "showNum": 0,
              "kv": "{\"biaoshi\":\"xiongyiwen\",\"people_state\":\"2\",\"uid\":\"1413830961943862\"}",
              "canVote": 1
            },
            {
              "oid": "0325004932030270",
              "text": "杨泊尼",
              "optionId": "94",
              "pageUrl": "",
              "picUrl": "https://u6.iqiyipic.com/feige/20210129/21/39/feige_3921eebda7434015a07f899f36facb78_default.jpg",
              "userCouldJoinTimes": 2,
              "userJoinTimes": 0,
              "todayHasJoined": false,
              "runTimes": 0,
              "showNum": 0,
              "kv": "{\"biaoshi\":\"yangboni\",\"people_state\":\"2\",\"uid\":\"1419653125514149\"}",
              "canVote": 1
            },
            {
              "oid": "0380977083030018",
              "text": "许卓伦",
              "optionId": "92",
              "pageUrl": "",
              "picUrl": "https://u3.iqiyipic.com/feige/20210129/13/7b/feige_7b13d1b5e2e24bacb1a23571424fdfaf_default.jpg",
              "userCouldJoinTimes": 2,
              "userJoinTimes": 0,
              "todayHasJoined": false,
              "runTimes": 0,
              "showNum": 0,
              "kv": "{\"biaoshi\":\"xuzhuolun\",\"people_state\":\"2\",\"uid\":\"1416286743721240\"}",
              "canVote": 1
            },
            {
              "oid": "1098251354030708",
              "text": "应晨熙",
              "optionId": "95",
              "pageUrl": "",
              "picUrl": "https://u8.iqiyipic.com/feige/20210129/2b/54/feige_542bcb21ddd74e649d71360abfdb269a_default.jpg",
              "userCouldJoinTimes": 2,
              "userJoinTimes": 0,
              "todayHasJoined": false,
              "runTimes": 0,
              "showNum": 0,
              "kv": "{\"biaoshi\":\"yingchenxi\",\"people_state\":\"2\",\"uid\":\"1395866053116839\"}",
              "canVote": 1
            },
            {
              "oid": "1442909847030298",
              "text": "杨皓钧",
              "optionId": "96",
              "pageUrl": "",
              "picUrl": "https://u2.iqiyipic.com/feige/20210129/1a/6b/feige_6b1a3bfbf9a2447a973d3bb030fc0a5c_default.jpg",
              "userCouldJoinTimes": 2,
              "userJoinTimes": 0,
              "todayHasJoined": false,
              "runTimes": 0,
              "showNum": 0,
              "kv": "{\"biaoshi\":\"yanghaojun\",\"people_state\":\"2\",\"uid\":\"1419448544142214\"}",
              "canVote": 1
            },
            {
              "oid": "1292102102030972",
              "text": "杨淘",
              "optionId": "99",
              "pageUrl": "",
              "picUrl": "https://u0.iqiyipic.com/feige/20210129/1b/ec/feige_ec1b98e5c87c45468f538124b0b49791_default.jpg",
              "userCouldJoinTimes": 2,
              "userJoinTimes": 0,
              "todayHasJoined": false,
              "runTimes": 0,
              "showNum": 0,
              "kv": "{\"biaoshi\":\"yangtao\",\"people_state\":\"2\",\"uid\":\"1399503689097715\"}",
              "canVote": 1
            },
            {
              "oid": "1216219294030996",
              "text": "杨约翰",
              "optionId": "102",
              "pageUrl": "",
              "picUrl": "https://u2.iqiyipic.com/feige/20210129/a0/fc/feige_fca094102eec4b4d9eb782d2413ade1f_default.jpg",
              "userCouldJoinTimes": 2,
              "userJoinTimes": 0,
              "todayHasJoined": false,
              "runTimes": 0,
              "showNum": 0,
              "kv": "{\"biaoshi\":\"yangyuehan\",\"people_state\":\"2\",\"uid\":\"1419655407207334\"}",
              "canVote": 1
            },
            {
              "oid": "0337765074030272",
              "text": "余衍隆",
              "optionId": "103",
              "pageUrl": "",
              "picUrl": "https://u7.iqiyipic.com/feige/20210129/35/f5/feige_f535984feb0d40d392c292b466c68dc0_default.jpg",
              "userCouldJoinTimes": 2,
              "userJoinTimes": 0,
              "todayHasJoined": false,
              "runTimes": 0,
              "showNum": 0,
              "kv": "{\"biaoshi\":\"yuyanlong\",\"people_state\":\"2\",\"uid\":\"1419503674065829\"}",
              "canVote": 1
            },
            {
              "oid": "0728732138030364",
              "text": "杨阳洋",
              "optionId": "104",
              "pageUrl": "",
              "picUrl": "https://u5.iqiyipic.com/feige/20210129/59/cd/feige_cd592f605dac415dbfa0e9660c3f5562_default.jpg",
              "userCouldJoinTimes": 2,
              "userJoinTimes": 0,
              "todayHasJoined": false,
              "runTimes": 0,
              "showNum": 0,
              "kv": "{\"biaoshi\":\"yangyangyang\",\"people_state\":\"2\",\"uid\":\"1416281274188271\"}",
              "canVote": 1
            },
            {
              "oid": "1238572948030104",
              "text": "杨智翔",
              "optionId": "105",
              "pageUrl": "",
              "picUrl": "https://u6.iqiyipic.com/feige/20210129/48/8e/feige_8e482ecd56114937a605f4acf9ee4568_default.jpg",
              "userCouldJoinTimes": 2,
              "userJoinTimes": 0,
              "todayHasJoined": false,
              "runTimes": 0,
              "showNum": 0,
              "kv": "{\"biaoshi\":\"yangzhixiang\",\"people_state\":\"2\",\"uid\":\"1410667986822019\"}",
              "canVote": 1
            },
            {
              "oid": "0610633248030030",
              "text": "钟福林",
              "optionId": "106",
              "pageUrl": "",
              "picUrl": "https://u1.iqiyipic.com/feige/20210129/7d/5f/feige_5f7dd6bca8424bd3a44682fb29b25234_default.jpg",
              "userCouldJoinTimes": 2,
              "userJoinTimes": 0,
              "todayHasJoined": false,
              "runTimes": 0,
              "showNum": 0,
              "kv": "{\"biaoshi\":\"zhongfulin\",\"people_state\":\"2\",\"uid\":\"1413859113968513\"}",
              "canVote": 1
            },
            {
              "oid": "0746340780030133",
              "text": "张景昀",
              "optionId": "107",
              "pageUrl": "",
              "picUrl": "https://u2.iqiyipic.com/feige/20210129/d6/5e/feige_5ed6d80af4814c2389b5dd4c62fe7880_default.jpg",
              "userCouldJoinTimes": 2,
              "userJoinTimes": 0,
              "todayHasJoined": false,
              "runTimes": 0,
              "showNum": 0,
              "kv": "{\"biaoshi\":\"zhangjingyun\",\"people_state\":\"2\",\"uid\":\"1413855288763324\"}",
              "canVote": 1
            },
            {
              "oid": "0222295468030508",
              "text": "赵瑾尧",
              "optionId": "108",
              "pageUrl": "",
              "picUrl": "https://u3.iqiyipic.com/feige/20210129/6b/32/feige_326bc744892d46c2aaee24d8a3934067_default.jpg",
              "userCouldJoinTimes": 2,
              "userJoinTimes": 0,
              "todayHasJoined": false,
              "runTimes": 0,
              "showNum": 0,
              "kv": "{\"biaoshi\":\"zhaojinyao\",\"people_state\":\"2\",\"uid\":\"1419552764351805\"}",
              "canVote": 1
            },
            {
              "oid": "0185361863030667",
              "text": "钟骏一",
              "optionId": "109",
              "pageUrl": "",
              "picUrl": "https://u2.iqiyipic.com/feige/20210129/72/43/feige_43724033bfcf40eb84b2ce4baf728760_default.jpg",
              "userCouldJoinTimes": 2,
              "userJoinTimes": 0,
              "todayHasJoined": false,
              "runTimes": 0,
              "showNum": 0,
              "kv": "{\"biaoshi\":\"zhongjunyi\",\"people_state\":\"2\",\"uid\":\"1416284461867506\"}",
              "canVote": 1
            },
            {
              "oid": "0479764348030908",
              "text": "赵明轩",
              "optionId": "111",
              "pageUrl": "",
              "picUrl": "https://u2.iqiyipic.com/feige/20210129/19/ac/feige_ac192b627b13442999fcb92e39321577_default.jpg",
              "userCouldJoinTimes": 2,
              "userJoinTimes": 0,
              "todayHasJoined": false,
              "runTimes": 0,
              "showNum": 0,
              "kv": "{\"biaoshi\":\"zhaomingxuan\",\"people_state\":\"2\",\"uid\":\"1410661947023842\"}",
              "canVote": 1
            },
            {
              "oid": "1203849858030453",
              "text": "周峻宇",
              "optionId": "110",
              "pageUrl": "",
              "picUrl": "https://u7.iqiyipic.com/feige/20210129/01/75/feige_7501cda02b294621b0ad28d113f53bbf_default.jpg",
              "userCouldJoinTimes": 2,
              "userJoinTimes": 0,
              "todayHasJoined": false,
              "runTimes": 0,
              "showNum": 0,
              "kv": "{\"biaoshi\":\"zhoujunyu\",\"people_state\":\"2\",\"uid\":\"1410413543555527\"}",
              "canVote": 1
            },
            {
              "oid": "0226296794030751",
              "text": "张帅博",
              "optionId": "112",
              "pageUrl": "",
              "picUrl": "https://u8.iqiyipic.com/feige/20210129/14/b5/feige_b514fb698d21479389c7478e3d2d556e_default.jpg",
              "userCouldJoinTimes": 2,
              "userJoinTimes": 0,
              "todayHasJoined": false,
              "runTimes": 0,
              "showNum": 0,
              "kv": "{\"biaoshi\":\"zhangshuaibo\",\"people_state\":\"2\",\"uid\":\"1395823942456580\"}",
              "canVote": 1
            },
            {
              "oid": "1435227641030958",
              "text": "哲野",
              "optionId": "115",
              "pageUrl": "",
              "picUrl": "https://u4.iqiyipic.com/feige/20210129/ce/56/feige_56ceca717ae74432a7af0992b7499ba2_default.jpg",
              "userCouldJoinTimes": 2,
              "userJoinTimes": 0,
              "todayHasJoined": false,
              "runTimes": 0,
              "showNum": 0,
              "kv": "{\"biaoshi\":\"zheye\",\"people_state\":\"2\",\"uid\":\"1419695034999243\"}",
              "canVote": 1
            },
            {
              "oid": "0518013693030593",
              "text": "湛展",
              "optionId": "117",
              "pageUrl": "",
              "picUrl": "https://u6.iqiyipic.com/feige/20210129/8d/6b/feige_6b8d387ecbe5416fb62895eb0220addf_default.jpg",
              "userCouldJoinTimes": 2,
              "userJoinTimes": 0,
              "todayHasJoined": false,
              "runTimes": 0,
              "showNum": 0,
              "kv": "{\"biaoshi\":\"zhanzhan\",\"people_state\":\"2\",\"uid\":\"1413831834206660\"}",
              "canVote": 1
            },
            {
              "oid": "0784847884030393",
              "text": "周子杰",
              "optionId": "118",
              "pageUrl": "",
              "picUrl": "https://u7.iqiyipic.com/feige/20210129/0f/6c/feige_6c0fb349aee44abea2411fc7554d4312_default.jpg",
              "userCouldJoinTimes": 2,
              "userJoinTimes": 0,
              "todayHasJoined": false,
              "runTimes": 0,
              "showNum": 0,
              "kv": "{\"biaoshi\":\"zhouzijie\",\"people_state\":\"2\",\"uid\":\"1413264093369649\"}",
              "canVote": 1
            },
            {
              "oid": "0111376008030047",
              "text": "钟卓融",
              "optionId": "119",
              "pageUrl": "",
              "picUrl": "https://u8.iqiyipic.com/feige/20210129/3f/0f/feige_0f3ff74a09354dc480cb2f5143b9e61d_default.jpg",
              "userCouldJoinTimes": 2,
              "userJoinTimes": 0,
              "todayHasJoined": false,
              "runTimes": 0,
              "showNum": 0,
              "kv": "{\"biaoshi\":\"zhongzhuorong\",\"people_state\":\"2\",\"uid\":\"1419467837940186\"}",
              "canVote": 1
            },
            {
              "oid": "1292575731030825",
              "text": "王梓澳",
              "optionId": "86",
              "pageUrl": "",
              "picUrl": "https://u1.iqiyipic.com/feige/20210129/7f/88/feige_887fc6899948482a95db4d6882817959_default.jpg",
              "userCouldJoinTimes": 2,
              "userJoinTimes": 0,
              "todayHasJoined": false,
              "runTimes": 0,
              "showNum": 0,
              "kv": "{\"biaoshi\":\"wangziao\",\"people_state\":\"4\",\"uid\":\"1399507615118623\"}",
              "canVote": 1
            }
          ]
        }
      ],
      "startTime": 1619262000,
      "endTime": 1620475200,
      "showJoinTimes": 0,
      "showJoinUsersCount": 0,
      "joinTotalTimes": 0,
      "perDayJoinTimes": 2,
      "perOptionJoinTimes": 0,
      "perDayOptionJoinTimes": 1,
      "status": 1,
      "remainVotesToday": 4,
      "vipCondition": {
        "joinTotalTimes": 0,
        "perdayJoinTimes": 4,
        "perOptionJoinTimes": 0,
        "perDayOptionJoinTimes": 2
      },
      "deleted": 0,
      "hasMoreVoteNum": 0,
      "childVotesVoteNum": []
    }
  },
  "msg": "success"
}